{
  "builds": [
    {
      "chipFamily": "ESP32",
      "parts": [
        {
          "offset": 4096,
          "path": "AtomVM-esp32-elixir-v0.6.6.img"
        }
      ]
    },
    {
      "chipFamily": "ESP32-C2",
      "parts": [
        {
          "offset": 0,
          "path": "AtomVM-esp32c2-elixir-v0.6.6.img"
        }
      ]
    },
    {
      "chipFamily": "ESP32-C3",
      "parts": [
        {
          "offset": 0,
          "path": "AtomVM-esp32c3-elixir-v0.6.6.img"
        }
      ]
    },
    {
      "chipFamily": "ESP32-C6",
      "parts": [
        {
          "offset": 0,
          "path": "AtomVM-esp32c6-elixir-v0.6.6.img"
        }
      ]
    },
    {
      "chipFamily": "ESP32-P4",
      "parts": [
        {
          "offset": 8192,
          "path": "AtomVM-esp32p4-elixir-v0.6.6.img"
        }
      ]
    },
    {
      "chipFamily": "ESP32-S2",
      "parts": [
        {
          "offset": 4096,
          "path": "AtomVM-esp32s2-elixir-v0.6.6.img"
        }
      ]
    },
    {
      "chipFamily": "ESP32-S3",
      "parts": [
        {
          "offset": 0,
          "path": "AtomVM-esp32s3-elixir-v0.6.6.img"
        }
      ]
    }
  ],
  "html_url": "https://github.com/atomvm/AtomVM/releases/tag/v0.6.6",
  "name": "AtomVM",
  "new_install_improv_wait_time": 0,
  "new_install_prompt_erase": true,
  "published_at": "2025-06-23T23:04:23Z",
  "version": "v0.6.6"
}